<configs>

	<!-- No Radiated Zombies -->
	<set xpath="/entitygroups/entitygroup[contains(@name, '')]/entity[contains(@name, 'zombieWightRadiated')]/@name">zombieMoe</set>
	<set xpath="/entitygroups/entitygroup[contains(@name, '')]/entity[contains(@name, 'zombieBoeRadiated')]/@name">zombieMoe</set>
	<set xpath="/entitygroups/entitygroup[contains(@name, '')]/entity[contains(@name, 'zombieFemaleFatRadiated')]/@name">zombieMoe</set>
	<set xpath="/entitygroups/entitygroup[contains(@name, '')]/entity[contains(@name, 'zombieJoeRadiated')]/@name">zombieMoe</set>
	<set xpath="/entitygroups/entitygroup[contains(@name, '')]/entity[contains(@name, 'zombieJanitorRadiated')]/@name">zombieMoe</set>
	<set xpath="/entitygroups/entitygroup[contains(@name, '')]/entity[contains(@name, 'zombieMoeRadiated')]/@name">zombieMoe</set>
	<set xpath="/entitygroups/entitygroup[contains(@name, '')]/entity[contains(@name, 'zombieArleneRadiated')]/@name">zombieMoe</set>
	<set xpath="/entitygroups/entitygroup[contains(@name, '')]/entity[contains(@name, 'zombieLabRadiated')]/@name">zombieMoe</set>
	<set xpath="/entitygroups/entitygroup[contains(@name, '')]/entity[contains(@name, 'zombieScreamerRadiated')]/@name">zombieMoe</set>
	<set xpath="/entitygroups/entitygroup[contains(@name, '')]/entity[contains(@name, 'zombieDarleneRadiated')]/@name">zombieMoe</set>
	<set xpath="/entitygroups/entitygroup[contains(@name, '')]/entity[contains(@name, 'zombieMarleneRadiated')]/@name">zombieMoe</set>
	<set xpath="/entitygroups/entitygroup[contains(@name, '')]/entity[contains(@name, 'zombieYoRadiated')]/@name">zombieMoe</set>
	<set xpath="/entitygroups/entitygroup[contains(@name, '')]/entity[contains(@name, 'zombieSteveRadiated')]/@name">zombieMoe</set>
	<set xpath="/entitygroups/entitygroup[contains(@name, '')]/entity[contains(@name, 'zombieSpiderRadiated')]/@name">zombieMoe</set>
	<set xpath="/entitygroups/entitygroup[contains(@name, '')]/entity[contains(@name, 'zombieFatCopRadiated')]/@name">zombieMoe</set>
	<set xpath="/entitygroups/entitygroup[contains(@name, '')]/entity[contains(@name, 'zombieSoldierRadiated')]/@name">zombieMoe</set>
	<set xpath="/entitygroups/entitygroup[contains(@name, '')]/entity[contains(@name, 'zombieSkateboarderRadiated')]/@name">zombieMoe</set>
	<set xpath="/entitygroups/entitygroup[contains(@name, '')]/entity[contains(@name, 'zombieCheerleaderRadiated')]/@name">zombieMoe</set>
	<set xpath="/entitygroups/entitygroup[contains(@name, '')]/entity[contains(@name, 'zombieOldTimerRadiated')]/@name">zombieMoe</set>
	<set xpath="/entitygroups/entitygroup[contains(@name, '')]/entity[contains(@name, 'zombieBikerRadiated')]/@name">zombieMoe</set>
</configs>